visorRobot/__init__.py
visorRobot/visor.py
visorRobot10-0.0.1.dist-info/METADATA
visorRobot10-0.0.1.dist-info/WHEEL
visorRobot10-0.0.1.dist-info/top_level.txt
visorRobot10-0.0.1.dist-info/RECORD
